debee/__init__.py
debee/__main__.py
debee/__main__.py-
debee/cmat2html.py
debee/color_map.py
debee/debee.py
debee/detect.py
debee/gen_cmat.py
debee/gen_filename.py
debee/loadparas.py
debee/remove_punct.py
debee/save_xlsx_tsv_csv.py
debee/text2lists.py
debee-0.1.1.dist-info/entry_points.txt
debee-0.1.1.dist-info/LICENSE
debee-0.1.1.dist-info/WHEEL
debee-0.1.1.dist-info/METADATA
debee-0.1.1.dist-info/RECORD
