Metadata-Version: 2.1
Name: debee
Version: 0.1.1
Summary: align german-english texts, fast
Home-page: https://github.com/ffreemt/debee
License: MIT
Author: ffreemt
Requires-Python: >=3.8.3,<4.0.0
Classifier: License :: OSI Approved :: MIT License
Classifier: Programming Language :: Python :: 3
Classifier: Programming Language :: Python :: 3.10
Classifier: Programming Language :: Python :: 3.9
Requires-Dist: aset2pairs (>=0.1.0,<0.2.0)
Requires-Dist: cmat2aset (==0.1.0a7)
Requires-Dist: de2en (>=0.1.1,<0.2.0)
Requires-Dist: fast-scores (>=0.1.2,<0.2.0)
Requires-Dist: fastlid (>=0.1.7,<0.2.0)
Requires-Dist: icecream (>=2.1.1,<3.0.0)
Requires-Dist: install (>=1.3.5,<2.0.0)
Requires-Dist: json-de2zh (>=0.1.1a0,<0.2.0)
Requires-Dist: logzero (>=1.7.0,<2.0.0)
Requires-Dist: set-loglevel (>=0.1.2,<0.2.0)
Requires-Dist: simplemma (>=0.3.0,<0.4.0)
Requires-Dist: typer (>=0.4.1,<0.5.0)
Project-URL: Repository, https://github.com/ffreemt/debee
